CHANGES.rst
MANIFEST.in
README.rst
lektor_diazo.py
setup.py
version.txt
lektor_diazotheme.egg-info/PKG-INFO
lektor_diazotheme.egg-info/SOURCES.txt
lektor_diazotheme.egg-info/dependency_links.txt
lektor_diazotheme.egg-info/entry_points.txt
lektor_diazotheme.egg-info/requires.txt
lektor_diazotheme.egg-info/top_level.txt