Metadata-Version: 1.1
Name: lektor-diazotheme
Version: 0.2
Summary: A package to postprocess html artifacts with diazo
Home-page: https://github.com/azazel75/lektor-diazotheme
Author: Alberto Berti
Author-email: alberto@metapensiero.it
License: LGPL3+
Platform: UNKNOWN
Classifier: Development Status :: 4 - Beta
Classifier: Programming Language :: Python
Classifier: Programming Language :: Python :: 2
Classifier: Programming Language :: Python :: 2.7
